{"lastUsed":1595197115158,"path":"\/Users\/ianleefmans\/Desktop\/Java_course","projectCount":14,"recentFiles":[{"path":"\/Lab-Switch\/src","parentWorkspace":"\/Users\/ianleefmans\/Desktop\/Java_course","name":"SwitchStatement.java","lastModified":1595197149489,"locationURI":"file:\/Users\/ianleefmans\/Desktop\/Java_course\/Lab-Switch\/src\/SwitchStatement.java"},{"path":"\/Lab-IfStatements\/src","parentWorkspace":"\/Users\/ianleefmans\/Desktop\/Java_course","name":"ExampleOne.java","lastModified":1595192675105,"locationURI":"file:\/Users\/ianleefmans\/Desktop\/Java_course\/Lab-IfStatements\/src\/ExampleOne.java"},{"path":"\/Lab-ElseStatements\/src","parentWorkspace":"\/Users\/ianleefmans\/Desktop\/Java_course","name":"ExampleOne.java","lastModified":1595194351635,"locationURI":"file:\/Users\/ianleefmans\/Desktop\/Java_course\/Lab-ElseStatements\/src\/ExampleOne.java"},{"path":"\/Lab-MultiArrays\/src","parentWorkspace":"\/Users\/ianleefmans\/Desktop\/Java_course","name":"MultiDimensionalArrays.java","lastModified":1595191432497,"locationURI":"file:\/Users\/ianleefmans\/Desktop\/Java_course\/Lab-MultiArrays\/src\/MultiDimensionalArrays.java"},{"path":"\/Lab-SwitchStatements\/src","parentWorkspace":"\/Users\/ianleefmans\/Desktop\/Java_course","name":"ExampleOne.java","lastModified":1595196425393,"locationURI":"file:\/Users\/ianleefmans\/Desktop\/Java_course\/Lab-SwitchStatements\/src\/ExampleOne.java"},{"path":"\/Lab Arrays\/src","parentWorkspace":"\/Users\/ianleefmans\/Desktop\/Java_course","name":"DisplayingArrays.java","lastModified":1595189233249,"locationURI":"file:\/Users\/ianleefmans\/Desktop\/Java_course\/Lab%20Arrays\/src\/DisplayingArrays.java"},{"path":"\/Lab-ElseIfStatements\/src","parentWorkspace":"\/Users\/ianleefmans\/Desktop\/Java_course","name":"ExampleOne.java","lastModified":1595195121738,"locationURI":"file:\/Users\/ianleefmans\/Desktop\/Java_course\/Lab-ElseIfStatements\/src\/ExampleOne.java"},{"path":"\/Lab-ConditionalBlocks\/src","parentWorkspace":"\/Users\/ianleefmans\/Desktop\/Java_course","name":"ConditionalBlocks.java","lastModified":1595195706595,"locationURI":"file:\/Users\/ianleefmans\/Desktop\/Java_course\/Lab-ConditionalBlocks\/src\/ConditionalBlocks.java"},{"path":"\/Lab-Datatypes\/src","parentWorkspace":"\/Users\/ianleefmans\/Desktop\/Java_course","name":"VariableDeclaration.java","lastModified":1595182149836,"locationURI":"file:\/Users\/ianleefmans\/Desktop\/Java_course\/Lab-Datatypes\/src\/VariableDeclaration.java"},{"path":"\/Lab-MathematicalOperator\/src","parentWorkspace":"\/Users\/ianleefmans\/Desktop\/Java_course","name":"MathematicalOperators.java","lastModified":1595185902543,"locationURI":"file:\/Users\/ianleefmans\/Desktop\/Java_course\/Lab-MathematicalOperator\/src\/MathematicalOperators.java"},{"path":"\/Lab-SwapElements\/src","parentWorkspace":"\/Users\/ianleefmans\/Desktop\/Java_course","name":"SwapElements.java","lastModified":1595190322369,"locationURI":"file:\/Users\/ianleefmans\/Desktop\/Java_course\/Lab-SwapElements\/src\/SwapElements.java"},{"path":"\/SecondProgram\/src\/package1","parentWorkspace":"\/Users\/ianleefmans\/Desktop\/Java_course","name":"PrintName.java","lastModified":1595179872122,"locationURI":"file:\/Users\/ianleefmans\/Desktop\/Java_course\/SecondProgram\/src\/package1\/PrintName.java"},{"path":"\/FirstProgram\/src\/program","parentWorkspace":"\/Users\/ianleefmans\/Desktop\/Java_course","name":"HelloWorld.java","lastModified":1595127440000},{"path":"\/Lab-CastingDatatypes\/src","parentWorkspace":"\/Users\/ianleefmans\/Desktop\/Java_course","name":"Examples.java","lastModified":1595186901050,"locationURI":"file:\/Users\/ianleefmans\/Desktop\/Java_course\/Lab-CastingDatatypes\/src\/Examples.java"},{"path":"\/Lab Arrays\/src","parentWorkspace":"\/Users\/ianleefmans\/Desktop\/Java_course","name":"ArrayLength.java","lastModified":1595189437625,"locationURI":"file:\/Users\/ianleefmans\/Desktop\/Java_course\/Lab%20Arrays\/src\/ArrayLength.java"}]}